llama_index/vector_stores/cogsearch/__init__.py
llama_index/vector_stores/cogsearch/base.py
llama_index_vector_stores_cogsearch-0.0.1.dist-info/METADATA
llama_index_vector_stores_cogsearch-0.0.1.dist-info/WHEEL
llama_index_vector_stores_cogsearch-0.0.1.dist-info/RECORD
