Metadata-Version: 2.1
Name: llama-index-vector-stores-cogsearch
Version: 0.0.1
Summary: llama-index vector_stores cogsearch integration
License: MIT
Author: Your Name
Author-email: you@example.com
Requires-Python: >=3.8.1,<3.12
Classifier: License :: OSI Approved :: MIT License
Classifier: Programming Language :: Python :: 3
Classifier: Programming Language :: Python :: 3.9
Classifier: Programming Language :: Python :: 3.10
Classifier: Programming Language :: Python :: 3.11
Requires-Dist: azure-search-documents (>=11.4.0,<12.0.0)
Requires-Dist: llama-index-core (>=0.9.32,<0.10.0)
